{
  "data": [
    {
      "created_at": "2021-11-27T21:25:24.000Z",
      "id": "1464706951892193281",
      "text": "@MarkGerretsen @polkaroo MEDSCAPE POLL: One in three doctors won't give Covid-19 vaccine to their own kids\n\nhttps://t.co/PIPpDxIImq"
    },
    {
      "created_at": "2021-11-27T21:25:24.000Z",
      "id": "1464706951661723652",
      "text": "@spectatorindex go fuxk yourself with your covid."
    },
    {
      "created_at": "2021-11-27T21:25:24.000Z",
      "id": "1464706950684450823",
      "text": "Secondary schools MUST run on-site Covid testing when pupils return after Christmas - https://t.co/NbJ5E8GJpy"
    },
    {
      "created_at": "2021-11-27T21:25:24.000Z",
      "id": "1464706949988204548",
      "text": "After such a fun year last season, this season has just been miserable. #Isles\n\nhttps://t.co/RwfUm4EeIi"
    },
    {
      "created_at": "2021-11-27T21:25:24.000Z",
      "id": "1464706948771684352",
      "text": "@APompliano New Covid variant (kinda but not really) and tanking markets\u2014lots on sale now. \ud83d\ude2c"
    },
    {
      "created_at": "2021-11-27T21:25:24.000Z",
      "id": "1464706948582952964",
      "text": "Covid-19 vaccine. https://t.co/lw4ynXoRlO"
    },
    {
      "created_at": "2021-11-27T21:25:23.000Z",
      "id": "1464706946011779074",
      "text": "Completely understood my point and referred me up the ladder which is to the California Dept of Public Heath. Called but they are closed today. Maybe there\u2019s nothing to this inquisition of mine and I just have Covid brain."
    },
    {
      "created_at": "2021-11-27T21:25:23.000Z",
      "id": "1464706945378664460",
      "text": "\u2018I think we\u2019re right to be concerned\u2019 \u2013 Dr De Gascun on new variant Omicron https://t.co/nC2u6pIv5Q well holy god another apostle to the covid hysterical gang, will he just piss off and let us live our lives now, we are finished with covid, we got our jabs  and  now take a hike"
    },
    {
      "created_at": "2021-11-27T21:25:22.000Z",
      "id": "1464706943784677380",
      "text": "Genomic testing for Omicron underway after COVID-positive South African passengers touch down in Sydney https://t.co/2cwCfD254A via @ABCaustralia"
    },
    {
      "created_at": "2021-11-27T21:25:22.000Z",
      "id": "1464706941041713153",
      "text": "@AbdRahman_KL @Cheriewingfiel1 @LozzaFox If you\u2019re worried about CVD, you need to worry about Covid. \n\nAlso your maths is out;\n\n17.9m -:- 12mth x 2.5mth = 3.7m CVD deaths\n\nTotal Global Covid deaths within 28 days = 5.2m\n\nThen add the deaths after 28 days. Plus no restrictions it\u2019d be far higher!\n\nhttps://t.co/jKeHcwPPLO"
    },
    {
      "created_at": "2021-11-27T21:25:22.000Z",
      "id": "1464706941012348933",
      "text": "@MistyMum2 It really is quite worrying. \n\nPeople just seem to have given up. \n\nMy other half was at the funeral of a work colleague who had died of Covid just last Monday. \n\nThis pandemic is far from over."
    },
    {
      "created_at": "2021-11-27T21:25:21.000Z",
      "id": "1464706937975496706",
      "text": "@GobiernoMX WHO Warn Governments Not to Rely on Vaccines Alone to Tackle Rising Covid-19 Rates\nhttps://t.co/QphEauGU9g"
    },
    {
      "created_at": "2021-11-27T21:25:21.000Z",
      "id": "1464706936453148678",
      "text": "&gt; At the time the U.S. had recorded 220,000 Covid deaths.\n\n&gt; Covid deaths this year have now surpassed the toll in 2020 with 350,000 since Inauguration Day."
    },
    {
      "created_at": "2021-11-27T21:25:21.000Z",
      "id": "1464706936398651402",
      "text": "@RTodKelly There are some other conservatives I\u2019ve liked, but they\u2019ve been driven too crazy by Trump, Covid, Kyle Rittenhouse or Covington Catholic.  Or they\u2019ve decided to sit out of the most important public conversations as bystanders."
    },
    {
      "created_at": "2021-11-27T21:25:21.000Z",
      "id": "1464706936054554626",
      "text": "The Fred Martinez Report:\"COVID-19 vaccines will kill people while making their underlying conditions appear to be the cause, prominent doctor warns\" ... https://t.co/YyhoKTLtuS"
    },
    {
      "created_at": "2021-11-27T21:25:21.000Z",
      "id": "1464706935597395969",
      "text": "@eyecandydf @ladyd2826 @TMZDeeDee And just because I have put it out there that I am not yet. Does not mean I will not be just means I have to have a doctor's permission first I do get covid tested and they do turn out negative. My seizures have to be controlled first"
    },
    {
      "created_at": "2021-11-27T21:25:19.000Z",
      "id": "1464706930350313474",
      "text": "With all these variants running around where is Shin Covid?"
    },
    {
      "created_at": "2021-11-27T21:25:19.000Z",
      "id": "1464706929222160385",
      "text": "this damn variant. covid u better not, i got concerts to attend"
    },
    {
      "created_at": "2021-11-27T21:25:18.000Z",
      "id": "1464706926093090816",
      "text": "@phiIsthiccbooty My moderna booster was the worst of the 3 unfortunately \ud83e\udd7a\ud83d\ude2e\ud83d\ude05. I was out for 24 hours... But almost everyone I know said the opposite..."
    },
    {
      "created_at": "2021-11-27T21:25:18.000Z",
      "id": "1464706925853962243",
      "text": "England places four more countries on Omicron Covid travel red list https://t.co/hF3A7Fv1K9"
    },
    {
      "created_at": "2021-11-27T21:25:18.000Z",
      "id": "1464706925535252481",
      "text": "@marcomendicino @MarkGerretsen @j_maloney MEDSCAPE POLL: One in three doctors won't give Covid-19 vaccine to their own kids\n\nhttps://t.co/PIPpDxIImq"
    },
    {
      "created_at": "2021-11-27T21:25:18.000Z",
      "id": "1464706925254352904",
      "text": "@KETV Lol. Except that it was discovered in 4 (fully) Covid vaccinated adults. Breakthrough Cases = Failed Vaccines. The continuance of Covid should inspire diet, exercise, VitC, VitD &amp; a good night\u2019s rest for immune support."
    },
    {
      "created_at": "2021-11-27T21:25:18.000Z",
      "id": "1464706925132759047",
      "text": "@uk_flames @BorisJohnson Boris is incapable of doing anything for someone other than himself. But some protection is better than none even before Covid you sneeze in a tissue.  I see a mask as something better than nothing. Not fear hope."
    },
    {
      "created_at": "2021-11-27T21:25:17.000Z",
      "id": "1464706919264833540",
      "text": "Andrew thinks youre 32,000 times more likely to die from Covid if unvaccinated. The ONS has been slapped down for trying to claim the figure is 32 times higher. You should probably ignore Andrew. https://t.co/8SbY3FOpqb"
    },
    {
      "created_at": "2021-11-27T21:25:16.000Z",
      "id": "1464706918056873990",
      "text": "Just got home from @Walgreens, a  mother came in with her 3 children coughing all over and asked the pharmacy technician where the home covid tests were located.\nI'm sorry but this should be an item you can buy at the drive thru window if you're sick.\nPut a note on the damn door!"
    },
    {
      "created_at": "2021-11-27T21:25:16.000Z",
      "id": "1464706917561995264",
      "text": "@JoyceHutchens3 It's why the morning my daughter came to me to say she felt sick, I barked \"Go to your room!\" (which she did immediately, we've discussed it, she's free to bark it at me in the same instance.  Fortunately, she did not have COVID.)"
    },
    {
      "created_at": "2021-11-27T21:25:16.000Z",
      "id": "1464706916160999426",
      "text": "Perfect storm brewing:\n- New variant, resetting COVID feedback loop to 2020\n- Like moths to a lamp, the branch COVIDians take #Omicron bait\n- They inevitably reinstate widely unpopular restrictions, shut schools, etc.\nI predict a total electoral blowout for Democrats is coming..."
    },
    {
      "created_at": "2021-11-27T21:25:16.000Z",
      "id": "1464706915255132172",
      "text": "@Charmunkle @MatthewMcCaff09 @WalterDavis4L @Mignon44 @NancyK07312478 @CNN Yes, the anti bodies get slightly reduced overtime with certain vaccines, like the covid and the influenza vaccines. Therefore, what you\u2019ll see is that every year people will take a covid shot"
    },
    {
      "created_at": "2021-11-27T21:25:16.000Z",
      "id": "1464706915221528576",
      "text": "@Meraki_IoM Massive Covid outbreak within the squad and Portuguese FA insisted they played. Believe the youth team are isolating too."
    },
    {
      "created_at": "2021-11-27T21:25:15.000Z",
      "id": "1464706914093260800",
      "text": "Where masks are mandatory\ud83d\udc47\ud83c\udffb\n https://t.co/tts3N03y9f"
    },
    {
      "created_at": "2021-11-27T21:25:15.000Z",
      "id": "1464706913766100992",
      "text": "@MyringNikolia @KimIversenShow It wasn\u2019t - this is the page from July - it was updated yesterday https://t.co/TjqgbgqXD3"
    },
    {
      "created_at": "2021-11-27T21:25:15.000Z",
      "id": "1464706912864411651",
      "text": "@SABCNews Where were these numbers during election campaigns, media coming in like a flood with COVID..I feel sorry for people who don't understand how media is used by the powerful to do their propagandas.."
    },
    {
      "created_at": "2021-11-27T21:25:15.000Z",
      "id": "1464706912486842377",
      "text": "Am I worried? Only worried about the bullshit panic that will likely ensue\u2026\n\nWhat you need to know about the Omicron COVID-19 variant https://t.co/nWOGhIQ79v"
    },
    {
      "created_at": "2021-11-27T21:25:15.000Z",
      "id": "1464706910741950467",
      "text": "Omicron variant spreads to Europe as UK announces countermeasures  https://t.co/C3e4idQs9d"
    },
    {
      "created_at": "2021-11-27T21:25:14.000Z",
      "id": "1464706908632330248",
      "text": "@fleetstreetfox Are you suggesting that vaccination stops a virus mutating?"
    },
    {
      "created_at": "2021-11-27T21:25:14.000Z",
      "id": "1464706907751337986",
      "text": "@komonews Time to stop blaming Covid and the pandemic for everything that goes wrong and be accountable for their inability to be competent leaders."
    },
    {
      "created_at": "2021-11-27T21:25:14.000Z",
      "id": "1464706907097157639",
      "text": "COVID-19: Two cases of Omicron variant detected in UK - with targeted testing to be rolled out in affected areas https://t.co/SElJCPRhUz"
    },
    {
      "created_at": "2021-11-27T21:25:14.000Z",
      "id": "1464706906543505412",
      "text": "@olives4fun @WhoseBacon @ToastTea369 @Finneganporter Restricted in France and Germany.\nhttps://t.co/bWVPbS1G0I."
    },
    {
      "created_at": "2021-11-27T21:25:14.000Z",
      "id": "1464706906233217026",
      "text": "@Jw6timesLfc @afowler06 Dieing with covid .... Was not dieing of covid wet wipe !"
    },
    {
      "created_at": "2021-11-27T21:25:14.000Z",
      "id": "1464706906216411139",
      "text": "Benfica are currently playing Belenenses tonight with the latter only being able to field 9 players due to Covid. \n\nTwo of the nine-man team are goal-keepers.\n\nIt's just got to HT: Belenenses 0-7 Benfica.\n\nShambles."
    },
    {
      "created_at": "2021-11-27T21:25:13.000Z",
      "id": "1464706905297797122",
      "text": "@sirspacedragon Glad you are past covid and getting back to the gym!"
    },
    {
      "created_at": "2021-11-27T21:25:13.000Z",
      "id": "1464706905205526529",
      "text": "The PCR test, which is considered the gold standard for detecting SARS Covid-2, is only about 70% accurate; not because the test is flawed (it\u2019s exquisitely accurate) but it\u2019s been proven that the virus is missed by the swab 30% of the time."
    },
    {
      "created_at": "2021-11-27T21:25:13.000Z",
      "id": "1464706905188806657",
      "text": "Now, with Gov. Gretchen Whitmer in Republicans' sites for defeat in 2022, they're accusing the Democratic chief executive of underplaying the coronavirus threat. \n\nThat's a significant reversal from February and March 2020.\n\nhttps://t.co/WimquAS3Zk"
    },
    {
      "created_at": "2021-11-27T21:25:13.000Z",
      "id": "1464706904467333123",
      "text": "@GOP From the party who REFUSE TO help the poor, spread lies &amp; allow memaw to die from Covid! Nor have any of you hypocrites wanted the stimulus checks to be distributed. Stfu! You inbred, diabolical idiots. Go spread Covid which what you do best!!!!! Unclean swine!!!\ud83d\udc3d\ud83d\udc3d\ud83d\udc3d\ud83d\udc3d\ud83d\udc3d"
    },
    {
      "created_at": "2021-11-27T21:25:13.000Z",
      "id": "1464706904060416000",
      "text": "@KFLAPH @MarkGerretsen MEDSCAPE POLL: One in three doctors won't give Covid-19 vaccine to their own kids\n\nhttps://t.co/PIPpDxIImq"
    },
    {
      "created_at": "2021-11-27T21:25:13.000Z",
      "id": "1464706903976648705",
      "text": "EXC: Gates Foundation Sent Over $54 Million To China Since COVID, Including To Wuhan Collaborators. https://t.co/PDGQ3FGwJz"
    },
    {
      "created_at": "2021-11-27T21:25:12.000Z",
      "id": "1464706901279662088",
      "text": "UK tightens Covid rules after finding Omicron\u00a0case https://t.co/gZXlpO7Qfo"
    },
    {
      "created_at": "2021-11-27T21:25:12.000Z",
      "id": "1464706900247855107",
      "text": "Mom shares near-death experience with COVID https://t.co/xMYaWYrZfS via @YouTube"
    },
    {
      "created_at": "2021-11-27T21:25:12.000Z",
      "id": "1464706900038397952",
      "text": "Whose side are you on? #covid #vaccinate #mask https://t.co/4sGl56RWq1"
    },
    {
      "created_at": "2021-11-27T21:25:12.000Z",
      "id": "1464706898775654414",
      "text": "@tannyo @SkepticalMutant @kath2cats @PaulDesmoParker @WendyOrent @provaxtexan @AudreysAmerica @handmadekathy @doom37455413 @ConsequentialBr @satekor @raouldukeerik @ogilville1 @Monstercoyliar @zeetubes @sammy44231 @tenebra99 @SultaneAlexand1 @deralteGaukler @andylumm @janem1276 @richykirsh @_mamadeb @JimeeLiberty @rpagano697 @Kathmarval @Tony__Heller @Fannyi5 @AndrewLazarus4 @sailor_man_dan @TechARP @runhack @CarvilleDean @MichaelBuerger8 @MsTrixter @DevoDalek @FactPhily @JamesLynchGTC @quintic @SoupTomatoSoup @WorldFullofJunk @andnowsheisnot @TyotoRiffle @pandemichoax21 @sasha13043803 @AriellaBrown @pds1st @Lilliputty @TellingNort @FillmoreWhite Only about 20% are asymptomatic\n\nhttps://t.co/xxVwjS8Uhp"
    },
    {
      "created_at": "2021-11-27T21:25:11.000Z",
      "id": "1464706896774926336",
      "text": "Omicron Scare in Bengaluru Prompts Fresh Curbs in Mumbai; BMC Issues Rules For Airport https://t.co/QnmDypbBcQ  does @CNNnews18 not know that BOM has flights coming from NBO and ADD, last I heard they were in Africa. @mybmc @CSMIA_Official @AnchorAnandN"
    },
    {
      "created_at": "2021-11-27T21:25:11.000Z",
      "id": "1464706893700603911",
      "text": "And here we had been told \u201cvaccination\u201d prevents ending up in the ICU. \ud83e\udd23\ud83e\udd21 #SmellsFishy https://t.co/o7vVWwCB0w"
    },
    {
      "created_at": "2021-11-27T21:25:10.000Z",
      "id": "1464706893469863937",
      "text": "Youngest tested positive for Covid today. I was up all night last night puking with a stomach bug. We could definitely use some prayers right now!"
    },
    {
      "created_at": "2021-11-27T21:25:10.000Z",
      "id": "1464706892924526593",
      "text": "@Terrordome74 @nextstrain George Soros, Bill Gates and the NWO. \n\n\ud83e\udd23\n\nGo tell Alex Jones! \n\nActually it was a MacArthur Genius Award and a Howard Hughes Medical Research grant. You obviously don\u2019t listen to NPR \ud83d\ude0f \n\nhttps://t.co/1gG5bw8Wk3"
    },
    {
      "created_at": "2021-11-27T21:25:10.000Z",
      "id": "1464706889695080448",
      "text": "@ChrisMasterjohn @AviBittMD Did you check with Alex?  Is it possible that Pfeizer would hide something? \ud83e\udd23 https://t.co/eQxLXg0Y7b"
    },
    {
      "created_at": "2021-11-27T21:25:09.000Z",
      "id": "1464706888369688576",
      "text": "@AlexisKat6 @angrybklynmom @txsalth2o @PNW_working_mom I see people ask what happened to independent doctors w.r.t. to covid. Yeah well its hard to exist on your own these days. Hospital admins have so much more power over policy and I think we're reaping what was sowed."
    },
    {
      "created_at": "2021-11-27T21:25:09.000Z",
      "id": "1464706887719395331",
      "text": "@normanswan This resistance to vaccination in South Africa, PNG, parts of the USA and elsewhere means that even when vaccines are available people will not accept vaccination on basis of religious belief and belief in conspiracy theories, and Covid spreads rapidly and very dangerously."
    },
    {
      "created_at": "2021-11-27T21:25:09.000Z",
      "id": "1464706887497105409",
      "text": "@Lee_Tennant Ask yourself why all those 200 other countries have not constructed purpose built quarantine facilities for COVID, and you will find the answer why they are just another political white elephant.\n\nNot even isolationist NZ has."
    },
    {
      "created_at": "2021-11-27T21:25:09.000Z",
      "id": "1464706887073546243",
      "text": "@GaelynnLea What people don't seem able to understand is that masks protect those around us better than they protect us. So NOT wearing a mask is not a risk to you, but those around you. Not wearing a mask means you have not bothered to understand COVID, or you don't care about others."
    },
    {
      "created_at": "2021-11-27T21:25:09.000Z",
      "id": "1464706886796779527",
      "text": "Covid in Scotland: Where are the latest cases? - BBC News https://t.co/cYE9njeeQG https://t.co/2Kk1G4vJHe"
    },
    {
      "created_at": "2021-11-27T21:25:09.000Z",
      "id": "1464706886784192517",
      "text": "Glad to see covid doesn\u2019t even exist anymore \ud83d\ude44 https://t.co/Hu6o36t90A"
    },
    {
      "created_at": "2021-11-27T21:25:09.000Z",
      "id": "1464706886029037568",
      "text": "@KRaux__ Ditto!!! I ended up getting the full Moderna dose, not the half size"
    },
    {
      "created_at": "2021-11-27T21:25:08.000Z",
      "id": "1464706884401709060",
      "text": "@TruthTaz Also people if you come across shit like this, report it for Misinformation on Health -&gt; Covid 19, easy."
    },
    {
      "created_at": "2021-11-27T21:25:08.000Z",
      "id": "1464706884145926161",
      "text": "Mask-wearing back for shops and transport and PCR tests for arrivals, PM announces https://t.co/SixhPcjq2c"
    },
    {
      "created_at": "2021-11-27T21:25:08.000Z",
      "id": "1464706883411918863",
      "text": "@JoanHeney @kearyshel @rtenews So you too are happy to 'live' with restrictions, i.e. present covid pass everytime you eat out, wear facemask indoors, have a vaccine every 5 months, etc. Their concerns are our conerns. We, vaccinated or not, want our freedoms back based on good science not based on coersion"
    },
    {
      "created_at": "2021-11-27T21:25:08.000Z",
      "id": "1464706883135148035",
      "text": "@samstein Aww, someones sad the narrative of blaming Trump for Covid deaths is now rightfully blaming Biden for more Covid deaths. \ud83e\udd21 https://t.co/EsL4W2Xac2"
    },
    {
      "created_at": "2021-11-27T21:25:08.000Z",
      "id": "1464706883135148032",
      "text": "@notSimon961 Omicron variant b.1.1.529 first reported back in July\n\nhttps://t.co/VwDX17nC3l"
    },
    {
      "created_at": "2021-11-27T21:25:08.000Z",
      "id": "1464706881969180672",
      "text": "@Norsecode5 @Localman850 @disclosetv I don't think that. I weighed up the risks and saw I was still waaaaay more vulnerable to covid than a jab. And also, you know, I do tend to think of what's best for everyone, not just me."
    },
    {
      "created_at": "2021-11-27T21:25:08.000Z",
      "id": "1464706881818091523",
      "text": "&gt; President Biden may not recall what he said during a 2020 campaign debate last fall, but Americans should: \u201cAnyone who is responsible for that many deaths should not remain as President of the United States of America.\u201d\nhttps://t.co/FDJ1JfSBeY"
    },
    {
      "created_at": "2021-11-27T21:25:08.000Z",
      "id": "1464706881713102852",
      "text": "@PosiePosie1212 @shahista210 @sitaravirgo @MdAntonieta @mohsinmalvi19 @shahwartaj07 @jiuerlily @tomorrow12River @hmn56656 @nhtrng18 @julystar69 @hcmr2015 @Cacallii He/she his/her immune system is strong enough to defend against the Attacks of Covid\n\nThe Hero Supper Carrier he/she is infected and cont. daily life = Covid19 in their body evolved around until it is stronger to knock out the patient.\n[mostly vaccinated patients]."
    },
    {
      "created_at": "2021-11-27T21:25:08.000Z",
      "id": "1464706881138556930",
      "text": "@outseide I got a Moderna booster at Bartell after two Pfizers."
    },
    {
      "created_at": "2021-11-27T21:25:07.000Z",
      "id": "1464706878953463827",
      "text": "@MSUownsOM NC state whoops yall if no Covid \ud83d\udc40"
    },
    {
      "created_at": "2021-11-27T21:25:07.000Z",
      "id": "1464706877858664454",
      "text": "Got my last Covid jab today.But enjoying the pool. #lakewoodranch @luxelr @ Luxe Lakewood Ranch https://t.co/UPrRKQMAGU"
    },
    {
      "created_at": "2021-11-27T21:25:07.000Z",
      "id": "1464706877531459587",
      "text": "@MarkGerretsen MEDSCAPE POLL: One in three doctors won't give Covid-19 vaccine to their own kids\n\nhttps://t.co/PIPpDxIImq"
    },
    {
      "created_at": "2021-11-27T21:25:06.000Z",
      "id": "1464706875857911809",
      "text": "News reports in Italy and Germany say that both countries have confirmed cases of the omicron COVID-19 variant. https://t.co/SAHuwbPqmJ"
    },
    {
      "created_at": "2021-11-27T21:25:06.000Z",
      "id": "1464706875597987840",
      "text": "@NashMcRonzie @MaS1banda @tarieTM @Twitter And giving covid a black face \ud83d\ude2d\ud83d\ude2d\ud83d\ude2d \n\nThis is turning into a nightmare for africans ."
    },
    {
      "created_at": "2021-11-27T21:25:06.000Z",
      "id": "1464706874843058177",
      "text": "I really fucking miss life before covid"
    },
    {
      "created_at": "2021-11-27T21:25:06.000Z",
      "id": "1464706874297700356",
      "text": "@ic_lib @Digvb31 @RNCResearch The US media framework has been fascinating to watch:\n\nCOVID deaths prior to January 20, 2021: Trump personally murdered them.\n\nRed-state COVID deaths after January 20, 2021: the Governor murdered them.\n\nBlue-state COVID deaths after January 20, 2021: unavoidable tragedy.\ud83d\ude22"
    },
    {
      "created_at": "2021-11-27T21:25:06.000Z",
      "id": "1464706873962156035",
      "text": "South African doctor who raised alarm about omicron variant says symptoms are \u2018unusual but mild\u2019 #covid https://t.co/rE6XO3YCyw"
    },
    {
      "created_at": "2021-11-27T21:25:06.000Z",
      "id": "1464706872561254411",
      "text": "@KP24 South Africa is dangerous, nothing to do with Covid but still dangerous."
    },
    {
      "created_at": "2021-11-27T21:25:06.000Z",
      "id": "1464706872523386886",
      "text": "More indication that omicron *might possibly* mean more severity in younger patients:\n\n\u201cWe\u2019re seeing a marked change in the demographic profile\u201d\n\n\u201cYoung people, in their 20s to just over their late 30s, are coming in with moderate to severe disease\u201d\n\nhttps://t.co/NW0Pgwk5l1 https://t.co/T1YSmbQZ9X"
    },
    {
      "created_at": "2021-11-27T21:25:05.000Z",
      "id": "1464706872255131649",
      "text": "@GovernorKayIvey How can we when you did not help your state. We are 5th in poverty and instead of sending the covid money to the people of Alabama, you decide to build 2 more prisons? \nI tell you what.. clean up the crime! What would you do IF you didn't get the covid relief funds??  People died"
    },
    {
      "created_at": "2021-11-27T21:25:05.000Z",
      "id": "1464706871818866689",
      "text": "@TinaFloresTX @ksorbs We could say the same for anyone who chooses to drink, smoke, or eat themselves into an early grave. Data shows obesity is a major factor in covid outcomes. Yet, we shrug that off. People act like this is shocking, but it's pretty common for people to ignore medical advice."
    },
    {
      "created_at": "2021-11-27T21:25:05.000Z",
      "id": "1464706870535458818",
      "text": "@statsjamie Actually suspect This all about getting boosters and Mask about Flu NHS is actually more worried about Flu than a new covid variant. cases of flu always go up in December. and lost of Elderly people have had covid booster but not flu jab"
    },
    {
      "created_at": "2021-11-27T21:25:05.000Z",
      "id": "1464706868647845892",
      "text": "The COVID-19 Pandemic has not been welcoming to many people. This is a suggestion to visit a therapist if Corona Virus has affected your financial situation, relationship, or general peace of mind."
    },
    {
      "created_at": "2021-11-27T21:25:04.000Z",
      "id": "1464706866852864002",
      "text": "@robinmckelvie This on FCDO:\nRules effective from 1 December 2021\nThe Spanish government requires all arrivals to Spain from the UK to present on entry a Health Control Form and a negative COVID-19 test; or proof of vaccination."
    },
    {
      "created_at": "2021-11-27T21:25:04.000Z",
      "id": "1464706865254830081",
      "text": "@rd_rubin @shabbat_col Today I prayed for no more COVID lockdowns. I NEED to make that trip \ud83d\ude4f\ud83c\udffb"
    },
    {
      "created_at": "2021-11-27T21:25:04.000Z",
      "id": "1464706864596271111",
      "text": "@HelenD_Dublin @Ann86084694 @kearyshel @rtenews \u201cmRNA vaccinations dramatically increase inflammation on the endothelium and T cell infiltration of cardiac muscle and may account for the observations of increased thrombosis, cardiomyopathy, and other vascular events following vaccination.\""
    },
    {
      "created_at": "2021-11-27T21:25:03.000Z",
      "id": "1464706863812034562",
      "text": "Look what happened to a similar flight in Holland. But in Clownland, we do nothing because we wouldn't want to in any way impede their ability to buy things in our European North Korean Brexit utopia. \n\nhttps://t.co/uGSaPbN989"
    },
    {
      "created_at": "2021-11-27T21:25:03.000Z",
      "id": "1464706861907656704",
      "text": "What to know about the newly discovered COVID-19 variant, according to a Johns Hopkins researcher https://t.co/BZ9VkksS0p via @Yahoo"
    },
    {
      "created_at": "2021-11-27T21:25:03.000Z",
      "id": "1464706861287018498",
      "text": "I think we're all pondering what's next w/new variant. Unverified thread here on Omicron covid variant. I was just about to dive into this topic w/u all. Let's keep an open mind. Again, I just read this and I have not verified anything. https://t.co/4kBKjlIHto"
    },
    {
      "created_at": "2021-11-27T21:25:02.000Z",
      "id": "1464706858166456332",
      "text": "BBC News - Covid: Travel and mask rules tightened over Omicron variant\nhttps://t.co/2TmdF1Ugfd I'm tired"
    },
    {
      "created_at": "2021-11-27T21:25:02.000Z",
      "id": "1464706856593629190",
      "text": "This holiday season, the @WorldBank @IMFNews and #G20 leaders should step up and redistribute their Special Drawing Rights to low- and middle-income countries to finance a global #COVID #pandemic response."
    },
    {
      "created_at": "2021-11-27T21:25:02.000Z",
      "id": "1464706856475975681",
      "text": "When the #pandemic hit, some hoped that it would unite a politically fractured America. Instead, writes @GeraldFSeib, it has deepened partisan divisions. #Covid  https://t.co/7QUnzqyxSD"
    },
    {
      "created_at": "2021-11-27T21:25:02.000Z",
      "id": "1464706856367104001",
      "text": "@SarahJH95 @emmakennytv Get vaccinated, wait a few weeks &amp; you shouldn\u2019t have to. Once enough people are vaccinated then herd immunity will be better placed to take over. The less people vaccinated, the longer covid goes on,the variants &amp; the longer we have to wear masks. Simple really"
    },
    {
      "created_at": "2021-11-27T21:25:02.000Z",
      "id": "1464706856182595592",
      "text": "Random thought for today!!  if technology wasn't as advanced as it is now eg. cell phones, social media do you think there would still be as big a push back against vaccination for Covid? Post your thoughts below."
    },
    {
      "created_at": "2021-11-27T21:25:02.000Z",
      "id": "1464706855905771520",
      "text": "North American markets tumble amid COVID variant worries.\nhttps://t.co/skhVXgtiDV"
    },
    {
      "created_at": "2021-11-27T21:25:01.000Z",
      "id": "1464706855373086725",
      "text": "Canadians to get biggest drop in gasoline prices since 2009 over COVID variant fears.\nhttps://t.co/zmhUutSuUw"
    },
    {
      "created_at": "2021-11-27T21:25:01.000Z",
      "id": "1464706854643281920",
      "text": "Packers elevate LB La'Darius Hamilton for gameday as COVID-19 replacement https://t.co/5n3o0iZi64"
    },
    {
      "created_at": "2021-11-27T21:25:01.000Z",
      "id": "1464706851749072899",
      "text": "@GOP Kamala buys a $375 dollar pot while Trump played golf costing American taxpayers well over $100 million dollars. https://t.co/TLyzaY4tuh"
    }
  ],
  "meta": {
    "newest_id": "1464706951892193281",
    "oldest_id": "1464706851749072899",
    "result_count": 100,
    "next_token": "b26v89c19zqg8o3fpdy797aen6y1e7bdrvq31wozdctj1"
  }
}